Metadata-Version: 1.1
Name: C-GPU
Version: 0.0.1
Summary: Mini virtual GPU made with the curses module!
Home-page: UNKNOWN
Author: Brandon Cannistraci
Author-email: fixerboy2009@gmail.com
License: MIT
Keywords: GPU
Platform: UNKNOWN
Classifier: Development Status :: 5 - Production/Stable
Classifier: Intended Audience :: Education
Classifier: Operating System :: Microsoft :: Windows :: Windows 10
Classifier: License :: OSI Approved :: MIT License
Classifier: Programming Language :: Python :: 3
